{
  "categorias": [
    { "id": "cat-1", "nombre": "Música", "descripcion": "Conciertos y festivales musicales de todos los géneros." },
    { "id": "cat-2", "nombre": "Cultura", "descripcion": "Exposiciones, teatro y actividades culturales." },
    { "id": "cat-3", "nombre": "Deportes", "descripcion": "Eventos deportivos y competencias en vivo." },
    { "id": "cat-4", "nombre": "Entretenimiento", "descripcion": "Comedia, shows y espectáculos familiares." }
  ],
  "eventos": [
    {
      "id": "ev-1",
      "codigo": "MORAT-2026",
      "nombre": "Morat - Antes de que Amanezca",
      "categoria": "Música",
      "precio": 120000,
      "fecha": "2026-10-18",
      "hora": "19:30",
      "ciudad": "Bogotá",
      "imagen": "evento6.jpg",
      "descripcion": "La banda de pop rock en español más importante del momento presenta su espectacular gira de estadios."
    },
    {
      "id": "ev-2",
      "codigo": "FEID-2026",
      "nombre": "Feid - Ferxxocalipsis Tour",
      "categoria": "Música",
      "precio": 150000,
      "fecha": "2026-11-05",
      "hora": "20:00",
      "ciudad": "Medellín",
      "imagen": "evento7.jpg",
      "descripcion": "El Ferxxo llega con el perreo más grande del año y una puesta en escena apocalíptica e inolvidable."
    },
    {
      "id": "ev-3",
      "codigo": "DUA-2026",
      "nombre": "Dua Lipa - Radical Optimism Tour",
      "categoria": "Música",
      "precio": 280000,
      "fecha": "2026-12-12",
      "hora": "21:00",
      "ciudad": "Bogotá",
      "imagen": "evento8.jpeg",
      "descripcion": "La superestrella del pop británico llega para encender el escenario con sus mayores éxitos globales."
    }
  ],
  "ventas": [
    {
      "id": "V-9901",
      "fecha": "2026-07-02T15:30:00",
      "ciudad": "Bogotá",
      "cliente": {
        "identificacion": "1020304050",
        "nombre": "Laura Gómez",
        "direccion": "Calle 45 #12-30",
        "telefono": "3001234567",
        "email": "laura.gomez@mail.com"
      },
      "items": [
        { "eventoId": "ev-1", "nombre": "Morat - Antes de que Amanezca", "precioUnit": 120000, "cantidad": 2, "subtotal": 240000 }
      ],
      "total": 240000
    }
  ],
  "metaVentas": 5000000
}